esc/__init__.py
esc/api.py
esc/enums.py
esc/responses.py
esc/triggers.py
esc/integrations/__init__.py
esc/integrations/openai/__init__.py
esc/integrations/openai/triggers.py
esc/integrations/openai/wrapper.py
esc_ai-0.0.1.dist-info/METADATA
esc_ai-0.0.1.dist-info/WHEEL
esc_ai-0.0.1.dist-info/entry_points.txt
esc_ai-0.0.1.dist-info/RECORD
